worldguess_pkg/__init__.py
worldguess-0.0.1.dist-info/LICENSE
worldguess-0.0.1.dist-info/METADATA
worldguess-0.0.1.dist-info/WHEEL
worldguess-0.0.1.dist-info/top_level.txt
worldguess-0.0.1.dist-info/RECORD
