Metadata-Version: 2.1
Name: worldguess
Version: 0.0.1
Summary: World Guess is a package to identify subject countries in documents
Home-page: https://github.com/Pumafi/worldguess
Author: FerdX
Author-email: ferdinand.bhavsar@epita.fr
License: UNKNOWN
Platform: UNKNOWN
Classifier: Programming Language :: Python :: 3
Classifier: License :: OSI Approved :: MIT License
Classifier: Operating System :: OS Independent
Requires-Python: >=3.6
Requires-Dist: pandas
